multibotkit/__init__.py
multibotkit/dispatchers/__init__.py
multibotkit/dispatchers/base_dispatcher.py
multibotkit/dispatchers/fb.py
multibotkit/dispatchers/telegram.py
multibotkit/dispatchers/viber.py
multibotkit/dispatchers/vk.py
multibotkit/helpers/__init__.py
multibotkit/helpers/base_helper.py
multibotkit/helpers/fb.py
multibotkit/helpers/telegram.py
multibotkit/helpers/viber.py
multibotkit/helpers/vk.py
multibotkit/schemas/__init__.py
multibotkit/schemas/fb/__init__.py
multibotkit/schemas/fb/incoming.py
multibotkit/schemas/fb/outgoing.py
multibotkit/schemas/telegram/__init__.py
multibotkit/schemas/telegram/incoming.py
multibotkit/schemas/telegram/outgoing.py
multibotkit/schemas/viber/__init__.py
multibotkit/schemas/viber/incoming.py
multibotkit/schemas/viber/outgoing.py
multibotkit/schemas/vk/__init__.py
multibotkit/schemas/vk/incoming.py
multibotkit/schemas/vk/outgoing.py
multibotkit/states/__init__.py
multibotkit/states/state.py
multibotkit/states/managers/__init__.py
multibotkit/states/managers/base.py
multibotkit/states/managers/memory.py
multibotkit/states/managers/mongo.py
multibotkit/states/managers/redis.py
multibotkit-0.1.34.dist-info/LICENSE
multibotkit-0.1.34.dist-info/METADATA
multibotkit-0.1.34.dist-info/WHEEL
multibotkit-0.1.34.dist-info/top_level.txt
multibotkit-0.1.34.dist-info/RECORD
