Metadata-Version: 2.1
Name: multibotkit
Version: 0.1.34
Summary: Functional library for developing multiplatform chatbots
Home-page: https://github.com/Appvelox/multibotkit
Author: Appvelox LLC
Author-email: team@appvelox.ru
Classifier: Intended Audience :: Developers
Classifier: Programming Language :: Python :: 3
Classifier: License :: OSI Approved :: MIT License
Classifier: Operating System :: OS Independent
Requires-Python: >=3.9
License-File: LICENSE
Requires-Dist: httpx>=0.23.0
Requires-Dist: pydantic<2
Requires-Dist: tenacity>=8.0.1
Requires-Dist: aiofiles>=22.1.0
Provides-Extra: mongo
Requires-Dist: motor>=3.0.0; extra == "mongo"
Provides-Extra: redis
Requires-Dist: redis>=4.6.0; extra == "redis"
